frenpy/__init__.py
frenpy/main.py
frenpy/words.json
FRENPY-0.3.6.dist-info/LICENSE
FRENPY-0.3.6.dist-info/METADATA
FRENPY-0.3.6.dist-info/WHEEL
FRENPY-0.3.6.dist-info/top_level.txt
FRENPY-0.3.6.dist-info/RECORD
