Metadata-Version: 2.1
Name: FRENPY
Version: 0.3.6
Summary: FRENPY is a french version of python
Author: slohwnix
Project-URL: Homepage, https://github.com/slohwnix/frenPY/
Project-URL: Issues, https://github.com/slohwnix/frenPY/issues
Classifier: Programming Language :: Python :: 3
Classifier: License :: OSI Approved :: MIT License
Classifier: Operating System :: OS Independent
Requires-Python: >=3.8
License-File: LICENSE
